AUTHORS
ChangeLog
LICENSE
MANIFEST.in
Makefile
README.rst
setup.cfg
setup.py
virtualenv.py
commandor/__init__.py
commandor/base.py
commandor/colors.py
commandor/compat.py
commandor/exceptions.py
commandor/utils.py
commandor.egg-info/PKG-INFO
commandor.egg-info/SOURCES.txt
commandor.egg-info/dependency_links.txt
commandor.egg-info/top_level.txt
examples/main.py
tests/__init__.py
tests/base.py
tests/core.py